{"name":"XVGOPT","id":"xvgopt_optimistic-ethereum","symbol":"xvgopt","description":"XVGOPT is the Optimism-based XVG-branded token that brings Verge’s ethos and value to one of the most scalable Layer 2 ecosystems on Ethereum. As part of the XVG token suite, it shares the same unified contract address across multiple chains, simplifying verification and integration. Paired exclusively with OP, the Optimism governance token, XVGOPT supports fast, low-cost transactions and future-ready DeFi applications and is backed by the Optimism layers value.","links":"https://XVGTokens.com","market_cap":23533,"market_cap_rank":9468,"logo":"https://raw.githubusercontent.com/Xellar-Protocol/xellar-assets/master/assets/xvgopt_optimistic-ethereum/logo.png","detail_platform":{"optimistic-ethereum":{"decimal_place":18,"contract_address":"0xe061aa40be525a13296cb4bf69f513242349d708","geckoterminal_url":"https://www.geckoterminal.com/optimism/tokens/0xe061aa40be525a13296cb4bf69f513242349d708"}},"is_native":false}