{"name":"3xcalibur Ecosystem Token","id":"3xcalibur","symbol":"xcal","description":"XCAL is the 3xcalibur Ecosystem Token. Issued on Arbitrum as a standard ERC-20 token. It can be vote-escrow locked into veXCAL for variable lengths and it serves multiple purposes such as: accruing platform fees and bribes, voting on gauges and being the de-facto governance token.","links":"https://3xcalibur.com","logo":"https://raw.githubusercontent.com/Xellar-Protocol/xellar-assets/master/assets/3xcalibur/logo.png"}