{"name":"Arky","id":"arky","symbol":"arky","description":"Introducing $ARKY, the meme token inspired by Arky, the beloved dog of Hal Finney, a pioneering cryptographer and a potential founder of Bitcoin. $ARKY aims to celebrate the legacy of Hal Finney by being the first \"Bitcoin dog\" token. As a tribute to Finney's impactful contributions to the cryptocurrency world, $ARKY embodies the spirit of innovation and loyalty. With its unique position in the crypto community, $ARKY seeks to lead a legacy that blends the historical significance of Bitcoin with the vibrant culture of meme tokens, engaging enthusiasts and collectors alike to partake in a playful yet meaningful digital currency experience. Join us as we embark on this exciting journey with $ARKY, where legacy and fun meet in the crypto space.","links":"https://arky-eth.com/","market_cap":0,"market_cap_rank":null,"logo":"https://raw.githubusercontent.com/Xellar-Protocol/xellar-assets/master/assets/arky/logo.png","detail_platform":{"ethereum":{"decimal_place":9,"contract_address":"0x9727eaf447203be268e5d471b6503bf47a71ea72","geckoterminal_url":"https://www.geckoterminal.com/eth/tokens/0x9727eaf447203be268e5d471b6503bf47a71ea72"}}}