{"name":"Shiba Nodes","id":"shiba-nodes","symbol":"shino","description":"As one of the Shibarium network’s validators, Shiba Nodes will play a crucial role in maintaining the integrity and stability of the network. We are excited to be a part of the Shibarium network and look forward to contributing to its success. We believe that our advanced security measures and a strong commitment to the network will make Shiba Nodes a trusted and reliable validator. So if you’re looking for a secure and reliable way to participate in the Shibarium network, look no further than buying and staking Shiba Nodes (SHINO).","links":"https://shibanodes.io","logo":"https://raw.githubusercontent.com/Xellar-Protocol/xellar-assets/master/assets/shiba-nodes/logo.png","detail_platform":{"ethereum":{"decimal_place":18,"contract_address":"0xe9287543684f440b2f29983a3472987bf7b0ed12"}}}