{"name":"Metaplex","id":"metaplex_solana","symbol":"mplx","description":"Metaplex (MPLX) is the standard for launching tokens and NFTs on Solana. Used to create 99% of tokens and NFTs on Solana, Metaplex powers the network’s biggest stablecoins, RWAs, DEXs, launchpads, wallets, DePIN networks, DeFi apps and games, with more than 900 million assets created and over $10 billion in transaction value. 50% of Metaplex protocol revenue is used to buy back MPLX for the Metaplex DAO.","links":"https://www.metaplex.com/","market_cap":32202658,"market_cap_rank":851,"logo":"https://raw.githubusercontent.com/Xellar-Protocol/xellar-assets/master/assets/metaplex_solana/logo.png","detail_platform":{"solana":{"decimal_place":6,"contract_address":"METAewgxyPbgwsseH8T16a39CQ5VyVxZi9zXiDPY18m","geckoterminal_url":"https://www.geckoterminal.com/solana/tokens/METAewgxyPbgwsseH8T16a39CQ5VyVxZi9zXiDPY18m"}},"is_native":false}