{"name":"Lena","id":"lena","symbol":"lena","description":"Lena (formerly known as MCG) has a mission to“Bridge the power of more emerging chains” and is committed to providing a highly secure, cross-chain experience for emerging chain projects and blockchain users. In view of the frequent cross-chain asset accidents, Lena took the lead to launch VoMEN network security solutions, significantly enhance cross-chain services. Lena is not a centralised product and only applies the asset hosting services provided by trusted custodians. Lena's cross-chain, product is absolutely decentralized, with dai-city casting and extraction of multiple signatures and multiple verifications, a mechanism in which asset custodians participate as third-party external verifiers across the chain","links":"https://microchains.network/","market_cap":0,"market_cap_rank":null,"logo":"https://raw.githubusercontent.com/Xellar-Protocol/xellar-assets/master/assets/lena/logo.png","detail_platform":{"ethereum":{"decimal_place":18,"contract_address":"0xfe38fd8d710b0ad367f60cb9fc4de5e7ba95633b"}}}