{"name":"Kendu","id":"kendu-inu_solana","symbol":"kendu","description":"Uniting the six native Japanese dog breeds. Kendu is the keeper of peace, the preserver of life, and the protector of unity. Join the pack!!","links":"https://kendu.io/","market_cap":5015832,"market_cap_rank":2068,"logo":"https://raw.githubusercontent.com/Xellar-Protocol/xellar-assets/master/assets/kendu-inu/logo.png","detail_platform":{"solana":{"decimal_place":8,"contract_address":"2nnrviYJRLcf2bXAxpKTRXzccoDbwaP4vzuGUG75Jo45","geckoterminal_url":"https://www.geckoterminal.com/solana/tokens/2nnrviYJRLcf2bXAxpKTRXzccoDbwaP4vzuGUG75Jo45"}},"is_native":false}