{"name":"Cronos","id":"crypto-com-chain_ethereum","symbol":"cro","description":"Cronos is an institutional-grade, high-performance, EVM-compatible Layer-1 blockchain built on the Cosmos SDK and integrated with the Inter-Blockchain Communication (IBC) protocol, designed as the backbone for open, compliant, and AI-accessible tokenized markets. It supports up to 60,000 transactions per second (TPS), 500ms block times, instant finality, and sub-$0.01 fees via Proof of Authority consensus.","links":"https://cronos.org/","market_cap":3677648923,"market_cap_rank":42,"logo":"https://raw.githubusercontent.com/Xellar-Protocol/xellar-assets/master/assets/crypto-com-chain/logo.png","detail_platform":{"ethereum":{"decimal_place":8,"contract_address":"0xa0b73e1ff0b80914ab6fe0444e65848c4c34450b","geckoterminal_url":"https://www.geckoterminal.com/eth/tokens/0xa0b73e1ff0b80914ab6fe0444e65848c4c34450b"}},"is_native":false}