{"name":"INSORA AI","id":"insora-ai","symbol":"$insora","description":"INSORA AI, a cutting-edge decentralized platform that empowers investors with advanced algorithmic trading bots. Our platform is designed to automate trading across various cryptocurrency markets, making it accessible for investors of all levels. INSORA AI leverages artificial intelligence and machine learning to optimize trading strategies, offering users the potential to earn passive income with minimal effort.","links":"https://insora.ai","market_cap":43200,"market_cap_rank":6748,"logo":"https://raw.githubusercontent.com/Xellar-Protocol/xellar-assets/master/assets/insora-ai/logo.png","detail_platform":{"ethereum":{"decimal_place":18,"contract_address":"0x94c6625371a59f3abe3b810c5d6f4e7c965d1b88"}}}