{"name":"CloudAI","id":"cloudai","symbol":"cloud","description":"CloudAI is a decentralized nation where AI and humans work together. AI agents automate tasks, provide services, and interact across platforms like X, Discord, and YouTube. is also a digital nation where 20+ AI agents, each with a specific role, work alongside humans. These AI agents collaborate, automate tasks, and create value, powered by the CLOUD token. New agents will be introduced progressively through community voting and milestone achievements.","links":"https://cloudaionbase.eth.limo/","market_cap":18260.06,"market_cap_rank":10091,"logo":"https://raw.githubusercontent.com/Xellar-Protocol/xellar-assets/master/assets/cloudai/logo.png","detail_platform":{"base":{"decimal_place":18,"contract_address":"0x2425598dd959e47a294a737ee4104316864817cf","geckoterminal_url":"https://www.geckoterminal.com/base/tokens/0x2425598dd959e47a294a737ee4104316864817cf"}}}