{"name":"2SHARE","id":"2share","symbol":"2shares","description":"2omb.finance is an incentive-oriented, high yield algorithmic stablecoin protocol that utilizes seigniorage mechanisms to bring $2OMB to a 1:1 price peg with Fantom.","links":"https://2omb.finance","market_cap":0,"market_cap_rank":null,"logo":"https://raw.githubusercontent.com/Xellar-Protocol/xellar-assets/master/assets/2share/logo.png","detail_platform":{"fantom":{"decimal_place":18,"contract_address":"0xc54a1684fd1bef1f077a336e6be4bd9a3096a6ca"}}}