{"name":"UTIX","id":"utix","symbol":"utx","description":"UTIX is an online e-ticketing platform that leverages blockchain technology to give event organizers greater control over ticket sales. Using smart contracts eliminates the inefficiencies associated with traditional ticketing platforms while maintaining user anonymity. Additionally, UTIX helps prevent counterfeit tickets and allows organizers to set secondary market prices, ultimately resolving the issue of ticket touts.","links":"https://utix.co.uk/","market_cap":0,"market_cap_rank":null,"logo":"https://raw.githubusercontent.com/Xellar-Protocol/xellar-assets/master/assets/utix/logo.png","detail_platform":{"ethereum":{"decimal_place":18,"contract_address":"0x958a03181806cb8807bef40e864e55f89b3393d3"}}}