{"name":"Solana Beach","id":"solana-beach_solana","symbol":"solana","description":"There is no Solana without Solana Beach. Solana Beach was the inspiration of Solana where the founders lived together.","links":"https://solanabeachsol.com/","market_cap":0,"market_cap_rank":null,"logo":"https://raw.githubusercontent.com/Xellar-Protocol/xellar-assets/master/assets/solana-beach_solana/logo.png","detail_platform":{"solana":{"decimal_place":9,"contract_address":"Ho2FQgg65oM1zpYuEnC8fULpBnWtqRCTrXRP56AeyCci","geckoterminal_url":"https://www.geckoterminal.com/solana/tokens/Ho2FQgg65oM1zpYuEnC8fULpBnWtqRCTrXRP56AeyCci"}},"is_native":false}