{"name":"ccFound","id":"ccfound-2","symbol":"found","description":"ccFOUND.com will be the biggest knowledge & wisdom search engine on the Internet. Connecting you with people, not computers!","links":"https://shop.ccfound.com/","market_cap":0,"market_cap_rank":null,"logo":"https://raw.githubusercontent.com/Xellar-Protocol/xellar-assets/master/assets/ccfound-2/logo.png","detail_platform":{"binance-smart-chain":{"decimal_place":18,"contract_address":"0x1acbc7d9c40aa8955281ae29b581bcf002eeb4f4"}}}