{"name":"CORGI CEO","id":"corgi-ceo","symbol":"corgiceo","description":"What is the project about? CORGI CEO a Meme token in the BSC ecosystem, $CORGICEO is a community project with a goal to advance into every aspect and day to day living of people all over the world. CORGI CEO is fully decentralized and owned by its fun, vibrant community. CORGI CEO enables groups of users to have access to a secure, SECURE and completely decentralized financial platform that aims to bring the power of wealth back where it belongs – In everyone's hands. Through harnessing the full potential of the community, decentralization and the Power of Blockchain. What makes your project unique? * CORGI CEO is fully decentralized and owned by its fun, vibrant community. * Who doesnt love cute Corgi right? Elon Musk thinks were pretty cool and invited me to be CEO of Twitter. * For every active user transaction a 7% $CORGICEO reward is granted to holders'; decentralized wallets only, fostering a healthy distributed network and community usage. * The $CORGICEO smart contract audited by a top specialized team and its LP (Liquidity Pool) tokens. * We have decided to Renounce Ownership of SMC and team dint hold tokens. History of your project. Initially build community and link with some partners. What’s next for your project? Product development What can your token be used for? * 5% Reflections for Helping to fill your bag with DOGE Hodlers CEO by giving you reflections. All you have to do is HODL. * 5% Marketing & Development Giving us the immediate resources we need to promote and actively drive new investors to purchase.","links":"https://corgiceo.com/","logo":"https://raw.githubusercontent.com/Xellar-Protocol/xellar-assets/master/assets/corgi-ceo/logo.png","detail_platform":{"binance-smart-chain":{"decimal_place":9,"contract_address":"0x365b475bc0eaf3c92f6b248b3f09d10f55ec900d"}}}