{"name":"Exp","id":"exp","symbol":"exp","description":"$EXP is the utility token of scholarz ecosystem (skoolverse) and will in future, be key to realize the potential of our ecosystem and play-and-earn and learn-and-earn model. Scholarz is a collection of non-fungible tokens (NFT) based on ERC721 standard living on Ethereum blockchain. Scholarz is a vision for future of education that circles around giving back and empowering others via games, education, and cryptocurrency.","links":"https://www.scholarz.io/","logo":"https://raw.githubusercontent.com/Xellar-Protocol/xellar-assets/master/assets/exp/logo.png","detail_platform":{"ethereum":{"decimal_place":18,"contract_address":"0xd137561c20be8e870d62e2ae92269f0950702f77"}}}