{"name":"SAUDI PEPE","id":"saudi-pepe","symbol":"saudipepe","description":"SAUDI PEPE is here to bring you infinite wealth. You missed the chance to be invested early in an extremely bullish memecoin and missed hundreds of millions of market caps and many Xs such as with $Doge or $SHIB or $PEPE? No problem! $SAUDIPEPE is destined to become one of the biggest memecoins and join the elite league. Be part of the incredible journey and feel the power of the Saudis! With utilities like NFTs, P2E Gaming, AI Services, Liquid Staking, SAUDI PEPE will be able to offer a variety of very interesting and useful things for its investors.","links":"https://saudipepecoin.com","logo":"https://raw.githubusercontent.com/Xellar-Protocol/xellar-assets/master/assets/saudi-pepe/logo.png","detail_platform":{"ethereum":{"decimal_place":18,"contract_address":"0x8acee0fcee91cedad1c5013f031762c814740587"}}}