{"name":"Sentinel Chain","id":"sentinel-chain","symbol":"senc","description":"The Sentinel Chain is a B2B marketplace specifically designed to provide affordable and secure financial services to the unbanked. Sentinel Chain aims to solve the following 1. Insurance 2. Loans 3. Collateral 4. Crowdfunding 5. Community Projects 6. E-Payments The project sees 2 major investors namely Fenbushi Capital and iGlobe Partners. There are also partnerships formed with Maybank, Medishares, Crowdo, and Vechain.","links":"https://sentinel-chain.org/","market_cap":101696,"market_cap_rank":4276,"logo":"https://raw.githubusercontent.com/Xellar-Protocol/xellar-assets/master/assets/sentinel-chain/logo.png","detail_platform":{"ethereum":{"decimal_place":18,"contract_address":"0xa13f0743951b4f6e3e3aa039f682e17279f52bc3"}}}