{"name":"WemergeToken","id":"wemergetoken","symbol":"mrg","description":"WEMERGE – The Global Leading Investment Strategist in Blockchain – integrates Blockchain investment fund, project acceleration, project evaluation and community operation, and uses decentralized tokenomics to distribute rights and interests among community members. We are committed to make every member a smarter and more professional blockchain participant. Our Vision is to be the Global Leading Investment Strategist in Blockchain. Our mission are to build a world decentralized and sustainable ecosystem for blockchain investment community, to create investment possibility to everyone, to accelerate potential international blockchain project and to provide sustainable investment strategy to the community. We focus on blockchain project investment, mining and block chain project acceleration. Wemerge is creating a healthy blockchain ecosystem that will bring blockchain venture capital, mining and project accelerator together and build a full ecological investment product for members of the community.","links":"http://www.wemerge.io","logo":"https://raw.githubusercontent.com/Xellar-Protocol/xellar-assets/master/assets/wemergetoken/logo.png","detail_platform":{"ethereum":{"decimal_place":18,"contract_address":"0xcbee6459728019cb1f2bb971dde2ee3271bc7617"}}}