{"name":"Star Wars Cat","id":"star-wars-cat","symbol":"swcat","description":"Star Wars Cat is a comprehensive metaverse gamefi protocol with lots of playing methods including interstellar card slot mining, feeding and growth, dividend system, breeding and trading, casino gambling.","links":"https://catplanet.finance/","market_cap":0,"market_cap_rank":null,"logo":"https://raw.githubusercontent.com/Xellar-Protocol/xellar-assets/master/assets/star-wars-cat/logo.png","detail_platform":{"binance-smart-chain":{"decimal_place":18,"contract_address":"0x98b6e33e77a55732f0e2ce595429144b18ce862c"}}}