{"name":"Souls of Meta","id":"souls-of-meta","symbol":"som","description":"Souls of Meta is a cross-game multi-chain Fun-2-Earn 3rd-person action RPG Fantasy NFT gaming metaverse of blades and sorcery where you can own, play, and monetize NFT assets through GameFi and SocialFi, and travel through community-created realms, fight monsters, collaborate with other players (PvE and PvP), solve quests and beyond, to have fun playing and earn at the same time!","links":"https://soulsofmeta.io/","logo":"https://raw.githubusercontent.com/Xellar-Protocol/xellar-assets/master/assets/souls-of-meta/logo.png","detail_platform":{"binance-smart-chain":{"decimal_place":9,"contract_address":"0x31c573d1a50a745b01862edaf2ae72017cea036a"}}}