{"name":"Alpine F1 Team Fan Token","id":"alpine-f1-team-fan-token_binance-smart-chain","symbol":"alpine","description":"Binance is excited to announce a pioneering partnership with BWT Alpine F1® Team, the first Formula 1 team to join the Binance Fan Token Platform. This partnership sees Binance become the official Fan Token partner of BWT Alpine F1® Team and the Alpine Esports partner from 2022 onwards. The Alpine F1® Team Fan Token (ALPINE) is a BEP-20 utility token to be launched first via the Binance Launchpad. ALPINE will then be available to all Binance users and the Binance Fan Token community via spot, bank card purchases, and P2P.","links":"https://www.binance.com/en/support/announcement/14f033f78d174d5e8ab0cabfd56dffb8","market_cap":5978273,"market_cap_rank":1947,"logo":"https://raw.githubusercontent.com/Xellar-Protocol/xellar-assets/master/assets/alpine-f1-team-fan-token/logo.png","detail_platform":{"binance-smart-chain":{"decimal_place":8,"contract_address":"0x287880ea252b52b63cc5f40a2d3e5a44aa665a76","geckoterminal_url":"https://www.geckoterminal.com/bsc/tokens/0x287880ea252b52b63cc5f40a2d3e5a44aa665a76"}},"is_native":false}