{"name":"CryptoBlades","id":"cryptoblades","symbol":"skill","description":"CryptoBlades is an NFT blockchain game on Binance Smart Chain","links":"https://www.cryptoblades.io/","market_cap":244301,"market_cap_rank":4296,"logo":"https://raw.githubusercontent.com/Xellar-Protocol/xellar-assets/master/assets/cryptoblades/logo.png","detail_platform":{"binance-smart-chain":{"decimal_place":18,"contract_address":"0x154a9f9cbd3449ad22fdae23044319d6ef2a1fab"},"polygon-pos":{"decimal_place":18,"contract_address":"0x863d6074afaf02d9d41a5f8ea83278df7089aa86"}}}