{"name":"ProspectorCrane","id":"prospectorcrane","symbol":"crane$","description":"CRANE$ Prospector is a Play2earn governance token, with dividends distribute automatically to holders! The token is deflationary, increasing the liquidity at each transaction and with an exclusive burn mechanism! The token is used for mint Miners and play the game, increasing its demands, as more players join the game! The Crane rewards! Holders receive frictionless Crane token rewards and also can stake the NFT to receive Crane rewards! Double win for holders and price increasing the main objective with this unique token smart contract.","links":"http://www.prospectornft.com/","logo":"https://raw.githubusercontent.com/Xellar-Protocol/xellar-assets/master/assets/prospectorcrane/logo.png"}