{"name":"CryptoFranc","id":"cryptofranc","symbol":"xchf","description":"CryptoFranc (XCHF) is an ERC-20 stablecoin issued by Swiss Crypto Tokens AG, representing a Swiss Franc denominated bond. All XCHF are fully backed by physical CHF bank notes which are audited by Grant Thornton Bank Audit Ltd on a monthly basis. Currently, 12’030’000 XCHF tokens are in circulation.","links":"https://www.bitcoinsuisse.com/cryptofranc","market_cap":1663938,"market_cap_rank":3360,"logo":"https://raw.githubusercontent.com/Xellar-Protocol/xellar-assets/master/assets/cryptofranc/logo.png","detail_platform":{"ethereum":{"decimal_place":18,"contract_address":"0xb4272071ecadd69d933adcd19ca99fe80664fc08"}}}