{"name":"DeHub","id":"dehub_base","symbol":"dhb","description":"DeHub is a gaming and streaming protocol powered by its own DePIN of shared computing power, enabling truly censorship-resistant content hosting, transcoding, and delivery. It is designed to solve major challenges faced by legacy media apps, including centralised moderation, demonetisation, deplatforming, limited monetisation options, lack of data ownership, and restricted creative freedom for content creators worldwide. First launched in 2021 by a team of proven social media experts, gamers, and entrepreneurs.","links":"https://www.dehub.io","market_cap":2635601,"market_cap_rank":2679,"logo":"https://raw.githubusercontent.com/Xellar-Protocol/xellar-assets/master/assets/dehub/logo.png","detail_platform":{"base":{"decimal_place":18,"contract_address":"0xd20ab1015f6a2de4a6fddebab270113f689c2f7c","geckoterminal_url":"https://www.geckoterminal.com/base/tokens/0xd20ab1015f6a2de4a6fddebab270113f689c2f7c"}},"is_native":false}