{"name":"Jeo Boden","id":"jeo-boden","symbol":"boden","description":"The $BODEN token, also known as the Joe Boden token, is a memecoin that humorously references Joe Biden.","links":"https://www.boden4pres.com/","market_cap":1878967,"market_cap_rank":3392,"logo":"https://raw.githubusercontent.com/Xellar-Protocol/xellar-assets/master/assets/jeo-boden/logo.png","detail_platform":{"solana":{"decimal_place":9,"contract_address":"3psH1Mj1f7yUfaD5gh6Zj7epE8hhrMkMETgv5TshQA4o","geckoterminal_url":"https://www.geckoterminal.com/solana/tokens/3psH1Mj1f7yUfaD5gh6Zj7epE8hhrMkMETgv5TshQA4o"}}}