{"name":"Fantom USD","id":"fantom-usd","symbol":"fusd","description":"Fantom offers the first DeFi stack built on an aBFT consensus. It’s much faster, cheaper, and more reliable and secure than its predecessors. On Fantom, you can use your FTM to mint fUSD and access the DeFi tools. You can use fUSD to trade synthetic assets, or lend it to earn interest and borrow synthetic tokens.","links":"https://fantom.foundation/defi/","market_cap":0,"market_cap_rank":null,"logo":"https://raw.githubusercontent.com/Xellar-Protocol/xellar-assets/master/assets/fantom-usd/logo.png","detail_platform":{"fantom":{"decimal_place":18,"contract_address":"0xad84341756bf337f5a0164515b1f6f993d194e1f"}}}