{"name":"BNB Card","id":"bnb-card","symbol":"bnbcard","description":"BNBCard is a memecoin on BSC. It was deployed because of the trending of https://bnb-card.vercel.app/. Even the cofounder of Binance He Yi has engaged with the BNB card. We have the unique narrative and most of the Chinese community and KOLs have shown interested in BNB Card. We have reached 30m+ trading volume in less than 20h. It was launched 20h ago (18th April) and CTOed by some Chinese holders. The community has planned for Twitter raiding and spaces along with meme contest. Also we have entered $4.4M Binance Liquidity Pool Support competition currently ranked as no.1.","links":"https://bnbcard-bsc.com/","market_cap":2507027,"market_cap_rank":3072,"logo":"https://raw.githubusercontent.com/Xellar-Protocol/xellar-assets/master/assets/bnb-card/logo.png","detail_platform":{"binance-smart-chain":{"decimal_place":18,"contract_address":"0xdc06717f367e57a16e06cce0c4761604460da8fc","geckoterminal_url":"https://www.geckoterminal.com/bsc/tokens/0xdc06717f367e57a16e06cce0c4761604460da8fc"}}}