{"name":"Damoon","id":"damoon","symbol":"damoon","description":"Fortoon favoors teh brev, and Mr. Damoon ain't no exceptiun. From teh moment he gazed at teh stars as a child, he knew his destinny was among 'em. Every tim a VVS whitelisted MEME token on Cronos reechs $10M Markit Cop or $3M Daily Trodding Volume, we burn 1% of total suppley, up to 20% of burn resorves.","links":"https://damooncoin.com/","market_cap":0,"market_cap_rank":null,"logo":"https://raw.githubusercontent.com/Xellar-Protocol/xellar-assets/master/assets/damoon/logo.png","detail_platform":{"cronos":{"decimal_place":18,"contract_address":"0x431469ce9d70a5879e959bf15cffad003dc7f69f"}}}